ocean_keeper/__init__.py
ocean_keeper/account.py
ocean_keeper/contract_base.py
ocean_keeper/contract_handler.py
ocean_keeper/diagnostics.py
ocean_keeper/didregistry.py
ocean_keeper/dispenser.py
ocean_keeper/event_filter.py
ocean_keeper/event_listener.py
ocean_keeper/exceptions.py
ocean_keeper/generic_contract.py
ocean_keeper/keeper.py
ocean_keeper/token.py
ocean_keeper/utils.py
ocean_keeper/wallet.py
ocean_keeper/web3_provider.py
ocean_keeper/agreements/__init__.py
ocean_keeper/agreements/agreement_manager.py
ocean_keeper/conditions/__init__.py
ocean_keeper/conditions/access.py
ocean_keeper/conditions/compute_execution.py
ocean_keeper/conditions/condition_base.py
ocean_keeper/conditions/condition_manager.py
ocean_keeper/conditions/escrow_reward.py
ocean_keeper/conditions/hash_lock.py
ocean_keeper/conditions/lock_reward.py
ocean_keeper/conditions/sign.py
ocean_keeper/conditions/threshold.py
ocean_keeper/conditions/white_listing.py
ocean_keeper/templates/__init__.py
ocean_keeper/templates/access_secret_store_template.py
ocean_keeper/templates/compute_execution_template.py
ocean_keeper/templates/template_base.py
ocean_keeper/templates/template_manager.py
ocean_keeper/web3/__init__.py
ocean_keeper/web3/contract.py
ocean_keeper/web3/http_provider.py
ocean_keeper/web3/request.py
ocean_keeper/web3/signature.py
ocean_keeper-0.3.5.dist-info/LICENSE
ocean_keeper-0.3.5.dist-info/METADATA
ocean_keeper-0.3.5.dist-info/WHEEL
ocean_keeper-0.3.5.dist-info/top_level.txt
ocean_keeper-0.3.5.dist-info/RECORD
